README.txt
ez_setup.py
setup.py
Products/__init__.py
Products.rpcauth.egg-info/PKG-INFO
Products.rpcauth.egg-info/SOURCES.txt
Products.rpcauth.egg-info/dependency_links.txt
Products.rpcauth.egg-info/namespace_packages.txt
Products.rpcauth.egg-info/not-zip-safe
Products.rpcauth.egg-info/requires.txt
Products.rpcauth.egg-info/top_level.txt
Products/rpcauth/__init__.py
Products/rpcauth/configure.zcml
Products/rpcauth/rpc.py
Products/rpcauth/tests/__init__.py
Products/rpcauth/tests/test_rpc.py