Metadata-Version: 1.0
Name: Products.rpcauth
Version: 0.1
Summary: Authentication queries to Zope over XML-RPC
Home-page: UNKNOWN
Author: Agendaless Consulting, Inc.
Author-email: mailto:tseaver@agendaless.com
License: ZPL
Platform: UNKNOWN
Classifier: Programming Language :: Python
